Workbook
Name Anos_Investidos: Simulador!$C$13
Name Dividendo_Mensal: Simulador!$C$18
Name Investimento_Mensal: Simulador!$C$11
Name Patrimonio_Acumulado: Simulador!$C$17
Name Rendimento_Carteira: Simulador!$C$6
Name Salario: Simulador!$C$4
Name Taxa_Rendimento: Simulador!$C$15

Sheet Instruções
B1: Instruções para Preenchimento da Planilha
B4: Na aba "Simulador", preencher apenas as células que estão em "Branco". As células em "Marrom" são células com preenchimento automático.

Sheet Simulador
A2: Simulador Estratégico de FIIs
B4: Salário | C4: 9500
B6: Rendimento Carteira | C6: 0.008
B8: Sugestão de investimento (30%) | C8: =Salario*30% -> 2850
B10: Investimento Mensal
B11: Investimento Mensal | C11: 2000
B13: Qtd. Anos | C13: 10
B15: Taxa de Rendimento | C15: 0.0108
B17: Patrimônio Acumulado | C17: =-FV(Taxa_Rendimento,Anos_Investidos*12,Investimento_Mensal) -> 486915.33
B18: Dividendo Mensal (Estimado) | C18: =Patrimonio_Acumulado*Rendimento_Carteira -> 3895.3227
C20: Filtro
B21: Perfil do Investidor | C21: Moderado
B23: Investimento Mensal | C23: =Investimento_Mensal -> 2000
B25: Tipo de FII
B26: =DT_Base!L3 -> Papel | C26: =DT_Base!$N$3 -> 640
B27: =DT_Base!L4 -> Tijolo | C27: =DT_Base!$N$4 -> 700
B28: =DT_Base!L5 -> Híbridos | C28: =DT_Base!$N$5 -> 160
B29: =DT_Base!L6 -> FOF's | C29: =DT_Base!$N$6 -> 100
B30: =DT_Base!L7 -> Desenvolvimento | C30: =DT_Base!$N$7 -> 200
B31: =DT_Base!L8 -> Hotelarias | C31: =DT_Base!$N$8 -> 200

Sheet DT_Base
B2: CHAVE | C2: PERFIL | D2: TIPO FII | E2: % | H2: Cenários | I2: Acumulado | J2: Dividendo | L2: TIPO DE FII | M2: % SUGERIDO | N2: VALORES
B3: =_xlfn.CONCAT(D3,"-",C3) -> Conservador-Papel | C3: Papel | D3: Conservador | E3: 0.3 | G3: 2 | H3: 2 Anos | I3: =-FV(Simulador!$C$15,DT_Base!G3*12,Simulador!$C$11) -> 54461.727 | J3: =I3*Rendimento_Carteira -> 435.69382 | L3: Papel | M3: =_xlfn.XLOOKUP(_xlfn.CONCAT(Simulador!$C$21,"-",L3),DT_Base!B:B,DT_Base!E:E,"Falso") -> 0.32 | N3: =Simulador!$C$23*M3 -> 640
B4: =_xlfn.CONCAT(D4,"-",C4) -> Conservador-Tijolo | C4: Tijolo | D4: Conservador | E4: 0.5 | G4: 5 | H4: 5 Anos | I4: =-FV(Simulador!$C$15,DT_Base!G4*12,Simulador!$C$11) -> 167608.04 | J4: =I4*Rendimento_Carteira -> 1340.8643 | L4: Tijolo | M4: =_xlfn.XLOOKUP(_xlfn.CONCAT(Simulador!$C$21,"-",L4),DT_Base!B:B,DT_Base!E:E,"Falso") -> 0.35 | N4: =Simulador!$C$23*M4 -> 700
B5: =_xlfn.CONCAT(D5,"-",C5) -> Conservador-Híbridos | C5: Híbridos | D5: Conservador | E5: 0.1 | G5: 10 | H5: 10 Anos | I5: =-FV(Simulador!$C$15,DT_Base!G5*12,Simulador!$C$11) -> 486915.33 | J5: =I5*Rendimento_Carteira -> 3895.3227 | L5: Híbridos | M5: =_xlfn.XLOOKUP(_xlfn.CONCAT(Simulador!$C$21,"-",L5),DT_Base!B:B,DT_Base!E:E,"Falso") -> 0.08 | N5: =Simulador!$C$23*M5 -> 160
B6: =_xlfn.CONCAT(D6,"-",C6) -> Conservador-FOF's | C6: FOF's | D6: Conservador | E6: 0.05 | G6: 15 | H6: 15 Anos | I6: =-FV(Simulador!$C$15,DT_Base!G6*12,Simulador!$C$11) -> 1095222.4 | J6: =I6*Rendimento_Carteira -> 8761.7789 | L6: FOF's | M6: =_xlfn.XLOOKUP(_xlfn.CONCAT(Simulador!$C$21,"-",L6),DT_Base!B:B,DT_Base!E:E,"Falso") -> 0.05 | N6: =Simulador!$C$23*M6 -> 100
B7: =_xlfn.CONCAT(D7,"-",C7) -> Conservador-Desenvolvimento | C7: Desenvolvimento | D7: Conservador | E7: 0.03 | G7: 20 | H7: 20 Anos | I7: =-FV(Simulador!$C$15,DT_Base!G7*12,Simulador!$C$11) -> 2254098 | J7: =I7*Rendimento_Carteira -> 18032.784 | L7: Desenvolvimento | M7: =_xlfn.XLOOKUP(_xlfn.CONCAT(Simulador!$C$21,"-",L7),DT_Base!B:B,DT_Base!E:E,"Falso") -> 0.1 | N7: =Simulador!$C$23*M7 -> 200
B8: =_xlfn.CONCAT(D8,"-",C8) -> Conservador-Hotelarias | C8: Hotelarias | D8: Conservador | E8: 0.02 | G8: 30 | H8: 30 Anos | I8: =-FV(Simulador!$C$15,DT_Base!G8*12,Simulador!$C$11) -> 8667809.6 | J8: =I8*Rendimento_Carteira -> 69342.477 | L8: Hotelarias | M8: =_xlfn.XLOOKUP(_xlfn.CONCAT(Simulador!$C$21,"-",L8),DT_Base!B:B,DT_Base!E:E,"Falso") -> 0.1 | N8: =Simulador!$C$23*M8 -> 200
B9: =_xlfn.CONCAT(D9,"-",C9) -> Moderado-Papel | C9: Papel | D9: Moderado | E9: 0.32 | G9: 40 | H9: 40 Anos | I9: =-FV(Simulador!$C$15,DT_Base!G9*12,Simulador!$C$11) -> 31945368 | J9: =I9*Rendimento_Carteira -> 255562.94 | L9: Total | N9: =SUM(N3:N8) -> 2000
B10: =_xlfn.CONCAT(D10,"-",C10) -> Moderado-Tijolo | C10: Tijolo | D10: Moderado | E10: 0.35 | G10: 50 | H10: 50 Anos | I10: =-FV(Simulador!$C$15,DT_Base!G10*12,Simulador!$C$11) -> 1.1642761e+08 | J10: =I10*Rendimento_Carteira -> 931420.84
B11: =_xlfn.CONCAT(D11,"-",C11) -> Moderado-Híbridos | C11: Híbridos | D11: Moderado | E11: 0.08
B12: =_xlfn.CONCAT(D12,"-",C12) -> Moderado-FOF's | C12: FOF's | D12: Moderado | E12: 0.05
B13: =_xlfn.CONCAT(D13,"-",C13) -> Moderado-Desenvolvimento | C13: Desenvolvimento | D13: Moderado | E13: 0.1
B14: =_xlfn.CONCAT(D14,"-",C14) -> Moderado-Hotelarias | C14: Hotelarias | D14: Moderado | E14: 0.1
B15: =_xlfn.CONCAT(D15,"-",C15) -> Agressivo-Papel | C15: Papel | D15: Agressivo | E15: 0.5
B16: =_xlfn.CONCAT(D16,"-",C16) -> Agressivo-Tijolo | C16: Tijolo | D16: Agressivo | E16: 0.1
B17: =_xlfn.CONCAT(D17,"-",C17) -> Agressivo-Híbridos | C17: Híbridos | D17: Agressivo | E17: 0.05
B18: =_xlfn.CONCAT(D18,"-",C18) -> Agressivo-FOF's | C18: FOF's | D18: Agressivo | E18: 0.05
B19: =_xlfn.CONCAT(D19,"-",C19) -> Agressivo-Desenvolvimento | C19: Desenvolvimento | D19: Agressivo | E19: 0.2
B20: =_xlfn.CONCAT(D20,"-",C20) -> Agressivo-Hotelarias | C20: Hotelarias | D20: Agressivo | E20: 0.1
